py2030/__init__.py
py2030/app.py
py2030/component_manager.py
py2030/event_manager.py
py2030/yaml.py
py2030/components/__init__.py
py2030/components/delay_events.py
py2030/components/event_to_event.py
py2030/components/event_to_omx.py
py2030/components/event_to_osc.py
py2030/components/midi_input.py
py2030/components/midi_to_event.py
py2030/components/midi_to_omx.py
py2030/components/midi_to_osc.py
py2030/components/omx_osc_output.py
py2030/components/omx_video_osc_input.py
py2030/components/omxsyncer.py
py2030/components/omxvideo.py
py2030/components/osc_input.py
py2030/components/osc_output.py
py2030/components/osc_to_event.py
py2030/components/osx_osc_video_resumer.py
py2030/components/ssh_remote.py
py2030/dependencies/OSC.py
py2030/dependencies/__init__.py
py2030/utils/__init__.py
py2030/utils/config_file.py
py2030-0.2.0.dist-info/DESCRIPTION.rst
py2030-0.2.0.dist-info/METADATA
py2030-0.2.0.dist-info/RECORD
py2030-0.2.0.dist-info/WHEEL
py2030-0.2.0.dist-info/metadata.json
py2030-0.2.0.dist-info/top_level.txt
py2030-0.2.0.dist-info/zip-safe
