Metadata-Version: 2.0
Name: py2030
Version: 0.2.0
Summary: A modular swiss pocket knife for managing a network of RaspberryPIs
Home-page: http://github.com/markkorput/py2030
Author: Mark van de Korput
Author-email: dr.theman@gmail.com
License: MIT
Platform: UNKNOWN
Requires-Dist: PyYAML (==3.11)
Requires-Dist: evento (==1.0.1)
Requires-Dist: omxplayer-wrapper (==0.0.2)
Requires-Dist: omxsync (==0.1.1)
Requires-Dist: pyOSC (==0.3.5b-5294)
